AUTHORS.txt
CHANGES.txt
DEVELOPERS.rst
LICENSE.txt
MANIFEST.in
README.rst
setup.cfg
setup.py
tox.ini
bin/git-flow
docs/Makefile
docs/_manpage-footer.rst
docs/_manpage-header.rst
docs/_subcmd-checkout.rst
docs/_subcmd-diff.rst
docs/_subcmd-finish.rst
docs/_subcmd-finish_version.rst
docs/_subcmd-list.rst
docs/_subcmd-publish.rst
docs/_subcmd-publish_version.rst
docs/_subcmd-pull.rst
docs/_subcmd-rebase.rst
docs/_subcmd-start.rst
docs/_subcmd-start_version.rst
docs/_subcmd-track.rst
docs/_subcmd-track_version.rst
docs/conf.py
docs/git-flow-feature.rst
docs/git-flow-hotfix.rst
docs/git-flow-init.rst
docs/git-flow-release.rst
docs/git-flow-status.rst
docs/git-flow-support.rst
docs/git-flow.rst
docs/index.rst
docs/html/.buildinfo
docs/html/genindex.html
docs/html/git-flow-feature.html
docs/html/git-flow-hotfix.html
docs/html/git-flow-init.html
docs/html/git-flow-release.html
docs/html/git-flow-status.html
docs/html/git-flow-support.html
docs/html/git-flow.html
docs/html/index.html
docs/html/objects.inv
docs/html/py-modindex.html
docs/html/search.html
docs/html/searchindex.js
docs/html/_static/ajax-loader.gif
docs/html/_static/basic.css
docs/html/_static/comment-bright.png
docs/html/_static/comment-close.png
docs/html/_static/comment.png
docs/html/_static/doctools.js
docs/html/_static/down-pressed.png
docs/html/_static/down.png
docs/html/_static/file.png
docs/html/_static/jquery.js
docs/html/_static/minus.png
docs/html/_static/nature.css
docs/html/_static/plus.png
docs/html/_static/pygments.css
docs/html/_static/searchtools.js
docs/html/_static/underscore.js
docs/html/_static/up-pressed.png
docs/html/_static/up.png
docs/html/_static/websupport.js
docs/html/reference/branches.html
docs/html/reference/core.html
docs/html/reference/index.html
docs/man/git-flow-feature.1
docs/man/git-flow-hotfix.1
docs/man/git-flow-init.1
docs/man/git-flow-release.1
docs/man/git-flow-status.1
docs/man/git-flow-support.1
docs/man/git-flow.1
docs/reference/branches.rst
docs/reference/core.rst
gitflow.egg-info/PKG-INFO
gitflow.egg-info/SOURCES.txt
gitflow.egg-info/dependency_links.txt
gitflow.egg-info/not-zip-safe
gitflow.egg-info/requires.txt
gitflow.egg-info/top_level.txt
