Metadata-Version: 1.1
Name: gitflow
Version: 0.5.1
Summary: Git extensions to provide high-level repository operations for Vincent Driessen's branching model.
Home-page: http://github.com/htgoebel/gitflow/
Author: Hartmut Goebel, Vincent Driessen
Author-email: h.goebel@crazy-compilers.com
License: BSD
Platform: any
Classifier: Development Status :: 4 - Beta
Classifier: Environment :: Console
Classifier: Intended Audience :: Developers
Classifier: License :: OSI Approved :: BSD License
Classifier: Operating System :: OS Independent
Classifier: Operating System :: POSIX
Classifier: Programming Language :: Python
Classifier: Topic :: Software Development :: Version Control
